Metadata-Version: 1.0
Name: Flask-WePay
Version: 0.0.7
Summary: WePay API support
Home-page: https://github.com/maxcountryman/flask-wepay
Author: Max Countryman
Author-email: maxc@me.com
License: BSD
Platform: any
Classifier: Environment :: Web Environment
Classifier: Intended Audience :: Developers
Classifier: License :: OSI Approved :: BSD License
Classifier: Operating System :: OS Independent
Classifier: Programming Language :: Python
Classifier: Topic :: Internet :: WWW/HTTP :: Dynamic Content
Classifier: Topic :: Software Development :: Libraries :: Python Modules
